LICENCE
MANIFEST.in
README.md
setup.py
thriftipy.py
Thriftipy.egg-info/PKG-INFO
Thriftipy.egg-info/SOURCES.txt
Thriftipy.egg-info/dependency_links.txt
Thriftipy.egg-info/not-zip-safe
Thriftipy.egg-info/top_level.txt