Metadata-Version: 1.1
Name: Thriftipy
Version: 0.0.1-dev
Summary: Tool for auto-generation and packaging thrift idls for Python
Home-page: http://github.com/barunsthakur/thriftipy
Author: Barun
Author-email: barunsthakur@gmail.com
License: MIT
Platform: Unix Like
Classifier: Programming Language :: Python
Classifier: Programming Language :: Python :: 3
Classifier: Topic :: Software Development :: Libraries
Classifier: License :: OSI Approved :: MIT License
